[
    {
        "name": "NEW_CARD_SCANNING_ENABLED",
        "version": "undefined"
    },
    {
        "name": "WC_SOLANA_TX_SIGN_ENABLED",
        "version": "5.18.0"
    },
    {
        "name": "STAKING_ENABLED",
        "version": "5.15.0"
    },
    {
        "name": "MARKETS_ENABLED",
        "version": "5.15.0"
    },
    {
        "name": "IS_ETHEREUM_EIP_1559_ENABLED",
        "version": "5.17.0"
    },
    {
        "name": "MIGRATE_USER_COUNTRY_CODE_ENABLED",
        "version": "5.17.0"
    },
    {
        "name": "ONRAMP_ENABLED",
        "version": "undefined"
    }
]
